verdi92_de_toolkit/__init__.py
verdi92_de_toolkit/main.py
verdi92_de_toolkit/vm.py
verdi92_de_toolkit-0.1.0.dist-info/METADATA
verdi92_de_toolkit-0.1.0.dist-info/WHEEL
verdi92_de_toolkit-0.1.0.dist-info/entry_points.txt
verdi92_de_toolkit-0.1.0.dist-info/RECORD
